petropandas/__init__.py
petropandas/constants.py
petropandas/database.py
petropandas/io.py
petropandas/minerals.py
petropandas/pandas_accessors.py
petropandas/data/__init__.py
petropandas/data/germ.json
petropandas/data/mnz/sbdata.csv
petropandas/data/oxides/avgpelite.csv
petropandas/data/oxides/bulk.csv
petropandas/data/oxides/grt_profile.csv
petropandas/data/oxides/minerals.csv
petropandas/data/oxides/pyroxenes.csv
petropandas-0.1.3.dist-info/METADATA
petropandas-0.1.3.dist-info/WHEEL
petropandas-0.1.3.dist-info/licenses/LICENSE
petropandas-0.1.3.dist-info/RECORD
