Metadata-Version: 2.4
Name: petropandas
Version: 0.1.3
Summary: Pandas accessors for petrologists
Project-URL: Homepage, https://github.com/ondrolexa/petropandas
Project-URL: Documentation, https://petropandas.readthedocs.io
Project-URL: Repository, https://github.com/ondrolexa/petropandas.git
Project-URL: Issues, https://github.com/ondrolexa/petropandas/issues
Maintainer-email: Ondrej Lexa <lexa.ondrej@gmail.com>
License-Expression: MIT
License-File: LICENSE
Classifier: License :: OSI Approved :: MIT License
Classifier: Operating System :: OS Independent
Classifier: Programming Language :: Python :: 3
Requires-Python: >=3.10
Requires-Dist: matplotlib
Requires-Dist: mpltern
Requires-Dist: numpy
Requires-Dist: openpyxl
Requires-Dist: pandas
Requires-Dist: periodictable
Requires-Dist: pyparsing
Requires-Dist: requests
Requires-Dist: seaborn
Requires-Dist: xlrd
Provides-Extra: dev
Requires-Dist: black; extra == 'dev'
Requires-Dist: jupyterlab; extra == 'dev'
Requires-Dist: mkdocs; extra == 'dev'
Requires-Dist: mkdocs-jupyter; extra == 'dev'
Requires-Dist: mkdocs-material; extra == 'dev'
Requires-Dist: mkdocstrings[python]; extra == 'dev'
Requires-Dist: nbval; extra == 'dev'
Requires-Dist: pytest; extra == 'dev'
Provides-Extra: docs
Requires-Dist: mkdocs; extra == 'docs'
Requires-Dist: mkdocs-jupyter; extra == 'docs'
Requires-Dist: mkdocs-material; extra == 'docs'
Requires-Dist: mkdocstrings[python]; extra == 'docs'
Provides-Extra: extra
Requires-Dist: jupyterlab; extra == 'extra'
Provides-Extra: tests
Requires-Dist: nbval; extra == 'tests'
Requires-Dist: pytest; extra == 'tests'
